genpylib/__init__.py
genpylib/ascii.py
genpylib/compile.py
genpylib/constants.py
genpylib/deploy.py
genpylib/generate.py
genpylib/run.py
genpylib-0.0.2.dist-info/METADATA
genpylib-0.0.2.dist-info/WHEEL
genpylib-0.0.2.dist-info/entry_points.txt
genpylib-0.0.2.dist-info/top_level.txt
genpylib-0.0.2.dist-info/RECORD
