Metadata-Version: 2.1
Name: genpylib
Version: 0.0.2
Summary: Easily generate and deploy python libraries to pypi.org
Home-page: https://github.com/frankhart2018/genpylib
Author: Siddhartha Dhar Choudhury
Author-email: sdharchou@gmail.com
License: MIT
Platform: UNKNOWN
Classifier: License :: OSI Approved :: MIT License
Classifier: Programming Language :: Python :: 3
Classifier: Programming Language :: Python :: 3.10
Classifier: Programming Language :: Python :: 3.9
Classifier: Programming Language :: Python :: 3.8
Classifier: Programming Language :: Python :: 3.7
Classifier: Programming Language :: Python :: 3.6
Requires-Dist: pipreqs
Requires-Dist: twine
Requires-Dist: simplpy
Requires-Dist: setuptools
